elasticecslogging/__init__.py
elasticecslogging/handlers.py
elasticecslogging/serializers.py
ElasticECSHandler-1.0.3.dist-info/LICENSE.md
ElasticECSHandler-1.0.3.dist-info/METADATA
ElasticECSHandler-1.0.3.dist-info/WHEEL
ElasticECSHandler-1.0.3.dist-info/top_level.txt
ElasticECSHandler-1.0.3.dist-info/RECORD
