Metadata-Version: 2.1
Name: ElasticECSHandler
Version: 1.0.3
Summary: Elasticsearch ECS Log handler for the logging library
Home-page: https://github.com/IMInterne/python-elasticsearch-ecs-logger
Author: IMInterne
Author-email: equipe_interne@innovmetric.com
License: Apache2
Keywords: logging elasticsearch handler ecs log django instrumentation
Platform: UNKNOWN
Classifier: Development Status :: 5 - Production/Stable
Classifier: Intended Audience :: Developers
Classifier: Topic :: System :: Logging
Classifier: Topic :: Software Development :: Libraries
Classifier: Topic :: Internet :: Log Analysis
Classifier: License :: OSI Approved :: Apache Software License
Classifier: Programming Language :: Python :: 2.7
Classifier: Programming Language :: Python :: 3.8
Requires-Dist: elasticsearch
Requires-Dist: requests
Requires-Dist: enum34 ; python_version<="3.4"
Provides-Extra: dev
Requires-Dist: check-manifest ; extra == 'dev'
Requires-Dist: six ; extra == 'dev'
Requires-Dist: pylint ; extra == 'dev'
Provides-Extra: test
Requires-Dist: coverage ; extra == 'test'
